[{"map_name":"new_map","map_id":"XWxl7tBYC5O2","map_description":"\nLast Modified Thu Oct 05 2017 13:26:07 GMT-0600 (Mountain Daylight Time)","homepage":"https://escher.github.io","schema":"https://escher.github.io/escher/jsonschema/1-0-0#"},{"reactions":{"0":{"name":"Aspartate kinase","bigg_id":"ASPK","reversibility":true,"label_x":-1239.6739501953125,"label_y":211.5361328125,"gene_reaction_rule":"b0002 or b3940 or b4024","genes":[{"notes":{"original_bigg_ids":["b0002"]},"name":"thrA","bigg_id":"b0002"},{"notes":{"original_bigg_ids":["b3940"]},"name":"metL","bigg_id":"b3940"},{"notes":{"original_bigg_ids":["b4024"]},"name":"lysC","bigg_id":"b4024"}],"metabolites":[{"bigg_id":"asp__L_c","coefficient":-1},{"bigg_id":"adp_c","coefficient":1},{"bigg_id":"atp_c","coefficient":-1},{"bigg_id":"4pasp_c","coefficient":1}],"segments":{"0":{"from_node_id":"1","to_node_id":"2","b1":null,"b2":null},"1":{"from_node_id":"3","to_node_id":"2","b1":null,"b2":null},"2":{"from_node_id":"1","to_node_id":"0","b1":{"x":-1259,"y":231.9999542236328},"b2":{"x":-1409.25,"y":231.9999542236328}},"3":{"from_node_id":"3","to_node_id":"4","b1":{"x":-1131,"y":231.9999542236328},"b2":{"x":-1125.75,"y":249.9999542236328}},"4":{"from_node_id":"1","to_node_id":"5","b1":{"x":-1263,"y":231.9999542236328},"b2":{"x":-1268.25,"y":249.9999542236328}},"5":{"from_node_id":"3","to_node_id":"6","b1":{"x":-1135,"y":231.9999542236328},"b2":{"x":-1080.75,"y":231.9999542236328}}}},"1":{"name":"Aspartate-semialdehyde dehydrogenase","bigg_id":"ASAD","reversibility":true,"label_x":-889.6739501953125,"label_y":211.5361328125,"gene_reaction_rule":"b3433","genes":[{"notes":{"original_bigg_ids":["b3433"]},"name":"asd","bigg_id":"b3433"}],"metabolites":[{"bigg_id":"aspsa_c","coefficient":-1},{"bigg_id":"nadp_c","coefficient":-1},{"bigg_id":"nadph_c","coefficient":1},{"bigg_id":"h_c","coefficient":1},{"bigg_id":"pi_c","coefficient":-1},{"bigg_id":"4pasp_c","coefficient":1}],"segments":{"6":{"from_node_id":"7","to_node_id":"8","b1":null,"b2":null},"7":{"from_node_id":"9","to_node_id":"8","b1":null,"b2":null},"8":{"from_node_id":"7","to_node_id":"10","b1":{"x":-785,"y":231.9999542236328},"b2":{"x":-730.75,"y":231.9999542236328}},"9":{"from_node_id":"7","to_node_id":"11","b1":{"x":-781,"y":231.9999542236328},"b2":{"x":-775.75,"y":213.9999542236328}},"10":{"from_node_id":"9","to_node_id":"12","b1":{"x":-913,"y":231.9999542236328},"b2":{"x":-918.25,"y":213.9999542236328}},"11":{"from_node_id":"9","to_node_id":"13","b1":{"x":-913,"y":231.9999542236328},"b2":{"x":-918.25,"y":249.9999542236328}},"12":{"from_node_id":"7","to_node_id":"14","b1":{"x":-781,"y":231.9999542236328},"b2":{"x":-780.634033203125,"y":249.9999542236328}},"13":{"from_node_id":"9","to_node_id":"6","b1":{"x":-909,"y":231.9999542236328},"b2":{"x":-963.25,"y":231.9999542236328}}}},"30":{"name":"Homoserine dehydrogenase (NADPH)","bigg_id":"HSDy","reversibility":true,"label_x":-654.5579833984375,"label_y":504.91273498535156,"gene_reaction_rule":"b3940 or b0002","genes":[{"notes":{"original_bigg_ids":["b3940"]},"name":"metL","bigg_id":"b3940"},{"notes":{"original_bigg_ids":["b0002"]},"name":"thrA","bigg_id":"b0002"}],"metabolites":[{"bigg_id":"hom__L_c","coefficient":-1},{"bigg_id":"aspsa_c","coefficient":1},{"bigg_id":"nadp_c","coefficient":-1},{"bigg_id":"nadph_c","coefficient":1},{"bigg_id":"h_c","coefficient":1}],"segments":{"189":{"from_node_id":"191","to_node_id":"192","b1":null,"b2":null},"190":{"from_node_id":"193","to_node_id":"192","b1":null,"b2":null},"191":{"from_node_id":"191","to_node_id":"194","b1":{"x":-669.5579833984375,"y":556.9127349853516},"b2":{"x":-669.5579833984375,"y":611.1627349853516}},"192":{"from_node_id":"193","to_node_id":"10","b1":{"x":-669.5579833984375,"y":432.91273498535156},"b2":{"x":-672,"y":290.7499542236328}},"193":{"from_node_id":"191","to_node_id":"195","b1":{"x":-669.5579833984375,"y":560.9127349853516},"b2":{"x":-687.5579833984375,"y":566.1627349853516}},"194":{"from_node_id":"193","to_node_id":"196","b1":{"x":-669.5579833984375,"y":428.91273498535156},"b2":{"x":-651.5579833984375,"y":423.66273498535156}},"195":{"from_node_id":"193","to_node_id":"197","b1":{"x":-669.5579833984375,"y":428.91273498535156},"b2":{"x":-682.6739501953125,"y":421.2207489013672}}}},"31":{"name":"Homoserine kinase","bigg_id":"HSK","reversibility":false,"label_x":-473.7393493652344,"label_y":647.0069122314453,"gene_reaction_rule":"b0003","genes":[{"notes":{"original_bigg_ids":["b0003"]},"name":"thrB","bigg_id":"b0003"}],"metabolites":[{"bigg_id":"phom_c","coefficient":1},{"bigg_id":"hom__L_c","coefficient":-1},{"bigg_id":"atp_c","coefficient":-1},{"bigg_id":"adp_c","coefficient":1},{"bigg_id":"h_c","coefficient":1}],"segments":{"196":{"from_node_id":"198","to_node_id":"199","b1":null,"b2":null},"197":{"from_node_id":"200","to_node_id":"199","b1":null,"b2":null},"198":{"from_node_id":"200","to_node_id":"201","b1":{"x":-373.949462890625,"y":669.9127349853516},"b2":{"x":-319.699462890625,"y":669.9127349853516}},"199":{"from_node_id":"198","to_node_id":"194","b1":{"x":-497.949462890625,"y":669.9127349853516},"b2":{"x":-610.8079833984375,"y":669.9127349853516}},"200":{"from_node_id":"198","to_node_id":"202","b1":{"x":-501.949462890625,"y":669.9127349853516},"b2":{"x":-507.199462890625,"y":687.9127349853516}},"201":{"from_node_id":"200","to_node_id":"203","b1":{"x":-369.949462890625,"y":669.9127349853516},"b2":{"x":-364.699462890625,"y":651.9127349853516}},"202":{"from_node_id":"200","to_node_id":"204","b1":{"x":-369.949462890625,"y":669.9127349853516},"b2":{"x":-364.699462890625,"y":687.9127349853516}}}},"32":{"name":"Threonine synthase","bigg_id":"THRS","reversibility":false,"label_x":-133.50743865966797,"label_y":649.4488677978516,"gene_reaction_rule":"b0004","genes":[{"notes":{"original_bigg_ids":["b0004"]},"name":"thrC","bigg_id":"b0004"}],"metabolites":[{"bigg_id":"phom_c","coefficient":-1},{"bigg_id":"thr__L_c","coefficient":1},{"bigg_id":"pi_c","coefficient":1},{"bigg_id":"h2o_c","coefficient":-1}],"segments":{"203":{"from_node_id":"205","to_node_id":"206","b1":null,"b2":null},"204":{"from_node_id":"207","to_node_id":"206","b1":null,"b2":null},"205":{"from_node_id":"205","to_node_id":"201","b1":{"x":-147.949462890625,"y":669.9127349853516},"b2":{"x":-202.199462890625,"y":669.9127349853516}},"206":{"from_node_id":"207","to_node_id":"208","b1":{"x":-23.949462890625,"y":669.9127349853516},"b2":{"x":28.509841918945312,"y":668.1220245361328}},"207":{"from_node_id":"207","to_node_id":"209","b1":{"x":-19.949462890625,"y":669.9127349853516},"b2":{"x":-14.699462890625,"y":687.9127349853516}},"208":{"from_node_id":"205","to_node_id":"210","b1":{"x":-151.949462890625,"y":669.9127349853516},"b2":{"x":-157.199462890625,"y":687.9127349853516}}}},"41":{"name":"L-threonine transport via ABC system (periplasm)","bigg_id":"THRabcpp","reversibility":false,"label_x":-209.32257461547852,"label_y":261.3770751953125,"gene_reaction_rule":"b3454 and b3455 and b3457 and b3460 and b3456","genes":[{"notes":{"original_bigg_ids":["b3454"]},"name":"livF","bigg_id":"b3454"},{"notes":{"original_bigg_ids":["b3455"]},"name":"livG","bigg_id":"b3455"},{"notes":{"original_bigg_ids":["b3457"]},"name":"livH","bigg_id":"b3457"},{"notes":{"original_bigg_ids":["b3460"]},"name":"livJ","bigg_id":"b3460"},{"notes":{"original_bigg_ids":["b3456"]},"name":"livM","bigg_id":"b3456"}],"metabolites":[{"bigg_id":"h2o_c","coefficient":-1},{"bigg_id":"atp_c","coefficient":-1},{"bigg_id":"thr__L_p","coefficient":-1},{"bigg_id":"h_c","coefficient":1},{"bigg_id":"adp_c","coefficient":1},{"bigg_id":"thr__L_c","coefficient":1},{"bigg_id":"pi_c","coefficient":1}],"segments":{"260":{"from_node_id":"267","to_node_id":"268","b1":null,"b2":null},"261":{"from_node_id":"269","to_node_id":"268","b1":null,"b2":null},"262":{"from_node_id":"267","to_node_id":"270","b1":{"x":-224.32257461547852,"y":185.3770751953125},"b2":{"x":-242.32257461547852,"y":180.1270751953125}},"263":{"from_node_id":"267","to_node_id":"271","b1":{"x":-213.5783576965332,"y":176.42355346679688},"b2":{"x":-206.32257461547852,"y":180.1270751953125}},"264":{"from_node_id":"267","to_node_id":"279","b1":{"x":-238.64821243286133,"y":-2.2281837463378906},"b2":{"x":-5.85676383972168,"y":-104.82719612121582}},"265":{"from_node_id":"269","to_node_id":"273","b1":{"x":-224.32257461547852,"y":317.3770751953125},"b2":{"x":-242.32257461547852,"y":322.6270751953125}},"266":{"from_node_id":"269","to_node_id":"274","b1":{"x":-224.32257461547852,"y":317.3770751953125},"b2":{"x":-206.32257461547852,"y":322.6270751953125}},"267":{"from_node_id":"269","to_node_id":"208","b1":{"x":-236.85750198364258,"y":510.3544616699219},"b2":{"x":26.37592315673828,"y":620.1162261962891}},"268":{"from_node_id":"269","to_node_id":"275","b1":{"x":-217.15976333618164,"y":310.2142639160156},"b2":{"x":-188.32257461547852,"y":307.6270751953125}}}},"42":{"name":"L-threonine reversible transport via proton symport (periplasm)","bigg_id":"THRt2rpp","reversibility":true,"label_x":89.72492599487305,"label_y":263.1677589416504,"gene_reaction_rule":"b3116","genes":[{"notes":{"original_bigg_ids":["b3116"]},"name":"tdcC","bigg_id":"b3116"}],"metabolites":[{"bigg_id":"thr__L_p","coefficient":-1},{"bigg_id":"thr__L_c","coefficient":1},{"bigg_id":"h_c","coefficient":1},{"bigg_id":"h_p","coefficient":-1}],"segments":{"269":{"from_node_id":"276","to_node_id":"277","b1":null,"b2":null},"270":{"from_node_id":"278","to_node_id":"277","b1":null,"b2":null},"271":{"from_node_id":"276","to_node_id":"279","b1":{"x":74.72492599487305,"y":191.1677589416504},"b2":{"x":65.77140045166016,"y":-85.12944984436035}},"272":{"from_node_id":"278","to_node_id":"208","b1":{"x":74.72492599487305,"y":315.1677589416504},"b2":{"x":81.88773345947266,"y":586.0928497314453}},"273":{"from_node_id":"278","to_node_id":"280","b1":{"x":74.72492599487305,"y":319.1677589416504},"b2":{"x":92.72492599487305,"y":324.4177589416504}},"274":{"from_node_id":"276","to_node_id":"281","b1":{"x":74.72492599487305,"y":187.1677589416504},"b2":{"x":92.72492599487305,"y":181.9177589416504}}}},"43":{"name":"L-threonine  via sodium symport (periplasm)","bigg_id":"THRt4pp","reversibility":false,"label_x":370.8653678894043,"label_y":261.3770751953125,"gene_reaction_rule":"b3089","genes":[{"notes":{"original_bigg_ids":["b3089"]},"name":"sstT","bigg_id":"b3089"}],"metabolites":[{"bigg_id":"na1_p","coefficient":-1},{"bigg_id":"thr__L_p","coefficient":-1},{"bigg_id":"thr__L_c","coefficient":1},{"bigg_id":"na1_c","coefficient":1}],"segments":{"275":{"from_node_id":"282","to_node_id":"283","b1":null,"b2":null},"276":{"from_node_id":"284","to_node_id":"283","b1":null,"b2":null},"277":{"from_node_id":"282","to_node_id":"285","b1":{"x":355.8653678894043,"y":185.3770751953125},"b2":{"x":373.8653678894043,"y":180.1270751953125}},"278":{"from_node_id":"282","to_node_id":"279","b1":{"x":370.19099044799805,"y":10.306737899780273},"b2":{"x":182.16714477539062,"y":-106.61788940429688}},"279":{"from_node_id":"284","to_node_id":"208","b1":{"x":384.5166130065918,"y":515.7265930175781},"b2":{"x":142.7716522216797,"y":620.1162261962891}},"280":{"from_node_id":"284","to_node_id":"287","b1":{"x":361.23749923706055,"y":312.0049743652344},"b2":{"x":373.8653678894043,"y":322.6270751953125}}}},"44":{"name":"L-threonine transport via diffusion (extracellular to periplasm)","bigg_id":"THRtex","reversibility":true,"label_x":-169.97281646728516,"label_y":-162.3910160064697,"gene_reaction_rule":"b0241 or b0929 or b1377 or b2215","genes":[{"notes":{"original_bigg_ids":["b0241"]},"name":"phoE","bigg_id":"b0241"},{"notes":{"original_bigg_ids":["b0929"]},"name":"ompF","bigg_id":"b0929"},{"notes":{"original_bigg_ids":["b1377"]},"name":"ompN","bigg_id":"b1377"},{"notes":{"original_bigg_ids":["b2215"]},"name":"ompC","bigg_id":"b2215"}],"metabolites":[{"bigg_id":"thr__L_p","coefficient":1},{"bigg_id":"thr__L_e","coefficient":-1}],"segments":{"281":{"from_node_id":"288","to_node_id":"289","b1":null,"b2":null},"282":{"from_node_id":"290","to_node_id":"289","b1":null,"b2":null},"283":{"from_node_id":"290","to_node_id":"279","b1":{"x":-49.01930236816406,"y":-143.87944984436035},"b2":{"x":5.2306976318359375,"y":-143.87944984436035}},"284":{"from_node_id":"288","to_node_id":"291","b1":{"x":-173.01930236816406,"y":-143.87944984436032},"b2":{"x":-227.26930236816406,"y":-143.87944984436032}}}},"45":{"name":"L-Threonine exchange","bigg_id":"EX_thr__L_e","reversibility":false,"label_x":-524.8117523193359,"label_y":-165.43921852111808,"gene_reaction_rule":"","genes":[],"metabolites":[{"bigg_id":"thr__L_e","coefficient":-1}],"segments":{"285":{"from_node_id":"292","to_node_id":"293","b1":null,"b2":null},"286":{"from_node_id":"294","to_node_id":"293","b1":null,"b2":null},"287":{"from_node_id":"292","to_node_id":"291","b1":{"x":-459.9032440185547,"y":-143.8794498443603},"b2":{"x":-344.76930236816406,"y":-143.8794498443603}}}},"46":{"name":"Phospho-L-threonine phosphatase (periplasmic)","bigg_id":"PTHRpp","reversibility":false,"label_x":403.86512756347656,"label_y":-167.76311683654785,"gene_reaction_rule":"b4055","genes":[{"notes":{"original_bigg_ids":["b4055"]},"name":"aphA","bigg_id":"b4055"}],"metabolites":[{"bigg_id":"pi_p","coefficient":1},{"bigg_id":"thr__L_p","coefficient":1},{"bigg_id":"thrp_p","coefficient":-1},{"bigg_id":"h2o_p","coefficient":-1}],"segments":{"288":{"from_node_id":"295","to_node_id":"296","b1":null,"b2":null},"289":{"from_node_id":"297","to_node_id":"296","b1":null,"b2":null},"290":{"from_node_id":"297","to_node_id":"298","b1":{"x":396.81861877441406,"y":-143.87944984436035},"b2":{"x":391.56861877441406,"y":-125.87944984436035}},"291":{"from_node_id":"297","to_node_id":"279","b1":{"x":400.81861877441406,"y":-143.87944984436035},"b2":{"x":122.73069763183594,"y":-143.87944984436035}},"292":{"from_node_id":"295","to_node_id":"299","b1":{"x":524.8186187744141,"y":-143.87944984436035},"b2":{"x":711.5806427001953,"y":-143.87944984436035}},"293":{"from_node_id":"295","to_node_id":"300","b1":{"x":528.8186187744141,"y":-143.87944984436035},"b2":{"x":534.0686187744141,"y":-125.87944984436035}}}},"50":{"name":"Phospho-L-threonine transport via diffusion (extracellular to periplasm)","bigg_id":"THRPtex","reversibility":true,"label_x":785.3306427001953,"label_y":41.12055015563965,"gene_reaction_rule":"b0241 or b0929 or b1377 or b2215","genes":[{"notes":{"original_bigg_ids":["b0241"]},"name":"phoE","bigg_id":"b0241"},{"notes":{"original_bigg_ids":["b0929"]},"name":"ompF","bigg_id":"b0929"},{"notes":{"original_bigg_ids":["b1377"]},"name":"ompN","bigg_id":"b1377"},{"notes":{"original_bigg_ids":["b2215"]},"name":"ompC","bigg_id":"b2215"}],"metabolites":[{"bigg_id":"thrp_e","coefficient":-1},{"bigg_id":"thrp_p","coefficient":1}],"segments":{"304":{"from_node_id":"311","to_node_id":"312","b1":null,"b2":null},"305":{"from_node_id":"313","to_node_id":"312","b1":null,"b2":null},"306":{"from_node_id":"311","to_node_id":"314","b1":{"x":770.3306427001953,"y":93.12055015563965},"b2":{"x":770.3306427001953,"y":147.37055015563965}},"307":{"from_node_id":"313","to_node_id":"299","b1":{"x":770.3306427001953,"y":-30.87944984436035},"b2":{"x":770.3306427001953,"y":-85.12944984436035}}}},"51":{"name":"L-Threonine O-3-phosphate exchange","bigg_id":"EX_thrp_e","reversibility":false,"label_x":787.1212921142578,"label_y":332.0273189544678,"gene_reaction_rule":"","genes":[],"metabolites":[{"bigg_id":"thrp_e","coefficient":-1}],"segments":{"308":{"from_node_id":"315","to_node_id":"316","b1":null,"b2":null},"309":{"from_node_id":"317","to_node_id":"316","b1":null,"b2":null},"310":{"from_node_id":"315","to_node_id":"314","b1":{"x":770.3306427001953,"y":319.12055015563965},"b2":{"x":770.3306427001953,"y":264.87055015563965}}}}},"nodes":{"0":{"node_type":"metabolite","x":-1468,"y":231.9999542236328,"bigg_id":"asp__L_c","name":"L-Aspartate","label_x":-1506.315966796875,"label_y":281.7680206298828,"node_is_primary":true},"1":{"node_type":"multimarker","x":-1217,"y":231.9999542236328},"2":{"node_type":"midmarker","x":-1197,"y":231.9999542236328},"3":{"node_type":"multimarker","x":-1177,"y":231.9999542236328},"4":{"node_type":"metabolite","x":-1092,"y":311.9999542236328,"bigg_id":"adp_c","name":"ADP","label_x":-1119,"label_y":351.9999542236328,"node_is_primary":false},"5":{"node_type":"metabolite","x":-1302,"y":311.9999542236328,"bigg_id":"atp_c","name":"ATP","label_x":-1329,"label_y":351.9999542236328,"node_is_primary":false},"6":{"node_type":"metabolite","x":-1022,"y":231.9999542236328,"bigg_id":"4pasp_c","name":"4-Phospho-L-aspartate","label_x":-1059.8,"label_y":276.8839874267578,"node_is_primary":true},"7":{"node_type":"multimarker","x":-827,"y":231.9999542236328},"8":{"node_type":"midmarker","x":-847,"y":231.9999542236328},"9":{"node_type":"multimarker","x":-867,"y":231.9999542236328},"10":{"node_type":"metabolite","x":-672,"y":231.9999542236328,"bigg_id":"aspsa_c","name":"L-Aspartate 4-semialdehyde","label_x":-634.0973022460937,"label_y":240.253662109375,"node_is_primary":true},"11":{"node_type":"metabolite","x":-742,"y":151.9999542236328,"bigg_id":"nadp_c","name":"Nicotinamide adenine dinucleotide phosphate","label_x":-774.4,"label_y":131.9999542236328,"node_is_primary":false},"12":{"node_type":"metabolite","x":-952,"y":151.9999542236328,"bigg_id":"nadph_c","name":"Nicotinamide adenine dinucleotide phosphate - reduced","label_x":-989.8,"label_y":131.9999542236328,"node_is_primary":false},"13":{"node_type":"metabolite","x":-952,"y":311.9999542236328,"bigg_id":"h_c","name":"H+","label_x":-936.453662109375,"label_y":320.25367736816406,"node_is_primary":false},"14":{"node_type":"metabolite","x":-746.884033203125,"y":311.9999542236328,"bigg_id":"pi_c","name":"Phosphate","label_x":-814.882470703125,"label_y":317.81166076660156,"node_is_primary":false},"191":{"node_type":"multimarker","x":-669.5579833984375,"y":514.9127349853516},"192":{"node_type":"midmarker","x":-669.5579833984375,"y":494.91273498535156},"193":{"node_type":"multimarker","x":-669.5579833984375,"y":474.91273498535156},"194":{"node_type":"metabolite","x":-669.5579833984375,"y":669.9127349853516,"bigg_id":"hom__L_c","name":"L-Homoserine","label_x":-712.9345703125,"label_y":718.7531890869141,"node_is_primary":true},"195":{"node_type":"metabolite","x":-749.5579833984375,"y":599.9127349853516,"bigg_id":"nadp_c","name":"Nicotinamide adenine dinucleotide phosphate","label_x":-803.5579833984375,"label_y":629.9127349853516,"node_is_primary":false},"196":{"node_type":"metabolite","x":-589.5579833984375,"y":389.91273498535156,"bigg_id":"nadph_c","name":"Nicotinamide adenine dinucleotide phosphate - reduced","label_x":-574.5579833984375,"label_y":389.91273498535156,"node_is_primary":false},"197":{"node_type":"metabolite","x":-744.6739501953125,"y":387.4707489013672,"bigg_id":"h_c","name":"H+","label_x":-803.4202880859375,"label_y":395.49256896972656,"node_is_primary":false},"198":{"node_type":"multimarker","x":-455.949462890625,"y":669.9127349853516},"199":{"node_type":"midmarker","x":-435.949462890625,"y":669.9127349853516},"200":{"node_type":"multimarker","x":-415.949462890625,"y":669.9127349853516},"201":{"node_type":"metabolite","x":-260.949462890625,"y":669.9127349853516,"bigg_id":"phom_c","name":"O-Phospho-L-homoserine","label_x":-298.2335266113281,"label_y":714.7968292236328,"node_is_primary":true},"202":{"node_type":"metabolite","x":-540.949462890625,"y":749.9127349853516,"bigg_id":"atp_c","name":"ATP","label_x":-567.949462890625,"label_y":789.9127349853516,"node_is_primary":false},"203":{"node_type":"metabolite","x":-330.949462890625,"y":589.9127349853516,"bigg_id":"adp_c","name":"ADP","label_x":-357.949462890625,"label_y":569.9127349853516,"node_is_primary":false},"204":{"node_type":"metabolite","x":-330.949462890625,"y":749.9127349853516,"bigg_id":"h_c","name":"H+","label_x":-347.149462890625,"label_y":789.9127349853516,"node_is_primary":false},"205":{"node_type":"multimarker","x":-105.949462890625,"y":669.9127349853516},"206":{"node_type":"midmarker","x":-85.949462890625,"y":669.9127349853516},"207":{"node_type":"multimarker","x":-65.949462890625,"y":669.9127349853516},"208":{"node_type":"metabolite","x":87.25984191894531,"y":668.1220245361328,"bigg_id":"thr__L_c","name":"L-Threonine","label_x":119.76252059936525,"label_y":673.9336700439453,"node_is_primary":true},"209":{"node_type":"metabolite","x":19.050537109375,"y":749.9127349853516,"bigg_id":"pi_c","name":"Phosphate","label_x":-2.5494628906249943,"label_y":789.9127349853516,"node_is_primary":false},"210":{"node_type":"metabolite","x":-190.949462890625,"y":749.9127349853516,"bigg_id":"h2o_c","name":"H2O","label_x":-217.949462890625,"label_y":789.9127349853516,"node_is_primary":false},"267":{"node_type":"multimarker","x":-224.32257461547852,"y":231.3770751953125},"268":{"node_type":"midmarker","x":-224.32257461547852,"y":251.3770751953125},"269":{"node_type":"multimarker","x":-224.32257461547852,"y":271.3770751953125},"270":{"node_type":"metabolite","x":-304.3225746154785,"y":146.3770751953125,"bigg_id":"h2o_c","name":"H2O","label_x":-349.3225746154785,"label_y":176.3770751953125,"node_is_primary":false},"271":{"node_type":"metabolite","x":-144.32257461547852,"y":146.3770751953125,"bigg_id":"atp_c","name":"ATP","label_x":-129.32257461547852,"label_y":146.3770751953125,"node_is_primary":false},"273":{"node_type":"metabolite","x":-304.3225746154785,"y":356.3770751953125,"bigg_id":"h_c","name":"H+","label_x":-331.3225746154785,"label_y":386.3770751953125,"node_is_primary":false},"274":{"node_type":"metabolite","x":-144.32257461547852,"y":356.3770751953125,"bigg_id":"adp_c","name":"ADP","label_x":-170.46864700317383,"label_y":389.2939147949219,"node_is_primary":false},"275":{"node_type":"metabolite","x":-64.32257461547852,"y":336.3770751953125,"bigg_id":"pi_c","name":"Phosphate","label_x":-49.322574615478516,"label_y":336.3770751953125,"node_is_primary":false},"276":{"node_type":"multimarker","x":74.72492599487305,"y":233.1677589416504},"277":{"node_type":"midmarker","x":74.72492599487305,"y":253.1677589416504},"278":{"node_type":"multimarker","x":74.72492599487305,"y":273.1677589416504},"279":{"node_type":"metabolite","x":63.98069763183594,"y":-143.87944984436035,"bigg_id":"thr__L_p","name":"L-Threonine","label_x":24.51537322998047,"label_y":-177.90281105041504,"node_is_primary":true},"280":{"node_type":"metabolite","x":154.72492599487305,"y":358.1677589416504,"bigg_id":"h_c","name":"H+","label_x":169.72492599487305,"label_y":358.1677589416504,"node_is_primary":false},"281":{"node_type":"metabolite","x":154.72492599487305,"y":148.1677589416504,"bigg_id":"h_p","name":"H+","label_x":169.72492599487305,"label_y":148.1677589416504,"node_is_primary":false},"282":{"node_type":"multimarker","x":355.8653678894043,"y":231.3770751953125},"283":{"node_type":"midmarker","x":355.8653678894043,"y":251.3770751953125},"284":{"node_type":"multimarker","x":355.8653678894043,"y":271.3770751953125},"285":{"node_type":"metabolite","x":435.8653678894043,"y":146.3770751953125,"bigg_id":"na1_p","name":"Sodium","label_x":450.8653678894043,"label_y":146.3770751953125,"node_is_primary":false},"287":{"node_type":"metabolite","x":435.8653678894043,"y":356.3770751953125,"bigg_id":"na1_c","name":"Sodium","label_x":450.8653678894043,"label_y":356.3770751953125,"node_is_primary":false},"288":{"node_type":"multimarker","x":-131.01930236816406,"y":-143.87944984436032},"289":{"node_type":"midmarker","x":-111.01930236816406,"y":-143.87944984436032},"290":{"node_type":"multimarker","x":-91.01930236816406,"y":-143.87944984436032},"291":{"node_type":"metabolite","x":-286.01930236816406,"y":-143.8794498443603,"bigg_id":"thr__L_e","name":"L-Threonine","label_x":-329.21930236816405,"label_y":-103.8794498443603,"node_is_primary":true},"292":{"node_type":"multimarker","x":-501.9032440185547,"y":-143.87944984436027},"293":{"node_type":"midmarker","x":-521.9032440185547,"y":-143.87944984436027},"294":{"node_type":"multimarker","x":-541.9032440185547,"y":-143.87944984436027},"295":{"node_type":"multimarker","x":482.81861877441406,"y":-143.87944984436035},"296":{"node_type":"midmarker","x":462.81861877441406,"y":-143.87944984436035},"297":{"node_type":"multimarker","x":442.81861877441406,"y":-143.87944984436035},"298":{"node_type":"metabolite","x":357.81861877441406,"y":-63.87944984436035,"bigg_id":"pi_p","name":"Phosphate","label_x":336.21861877441404,"label_y":-23.87944984436035,"node_is_primary":false},"299":{"node_type":"metabolite","x":770.3306427001953,"y":-143.87944984436035,"bigg_id":"thrp_p","name":"L-Threonine O-3-phosphate","label_x":737.9306427001953,"label_y":-177.29828071594238,"node_is_primary":true},"300":{"node_type":"metabolite","x":567.8186187744141,"y":-63.87944984436035,"bigg_id":"h2o_p","name":"H2O","label_x":540.8186187744141,"label_y":-23.87944984436035,"node_is_primary":false},"311":{"node_type":"multimarker","x":770.3306427001953,"y":51.12055015563965},"312":{"node_type":"midmarker","x":770.3306427001953,"y":31.12055015563965},"313":{"node_type":"multimarker","x":770.3306427001953,"y":11.120550155639648},"314":{"node_type":"metabolite","x":770.3306427001953,"y":206.12055015563965,"bigg_id":"thrp_e","name":"L-Threonine O-3-phosphate","label_x":801.5025787353516,"label_y":212.29245567321777,"node_is_primary":true},"315":{"node_type":"multimarker","x":770.3306427001953,"y":361.12055015563965},"316":{"node_type":"midmarker","x":770.3306427001953,"y":381.12055015563965},"317":{"node_type":"multimarker","x":770.3306427001953,"y":401.12055015563965}},"text_labels":{"0":{"x":-1614,"y":181.99989318847656,"text":"L-Aspartate"},"4":{"x":74.2026596069336,"y":742.4086303710938,"text":"L-Threonine"},"12":{"x":-869.234130859375,"y":-159.80992889404297,"text":"Extracellular"},"13":{"x":-865.6527709960938,"y":-100.71672058105469,"text":"L-Threonine"},"14":{"x":643.9102172851562,"y":466.9362487792969,"text":"Extracellular"},"15":{"x":480.95635986328125,"y":518.8666687011719,"text":"L-Threonine O-3-phosphate"}},"canvas":{"x":-1664.0328369140625,"y":-412.390380859375,"width":2851.455810546875,"height":1267.1925659179688}}]